Workbook

Sheet Appraisal Summary
A1: CANARA BANK - CREDIT APPRAISAL SUMMARY
A3: 1. BORROWER PROFILE
A4: Borrower Name | B4: M/S. MALUSARE ENTERPRISES
A5: Business Type | B5: Transport/Automobile - Canara Vahan
A6: Proprietor | B6: MRS. SHILA KISHOR MALUSARE
A7: Experience | B7: To be verified from documents
A8: Location | B8: Mumbai, Maharashtra
A10: 2. LOAN PARTICULARS
A11: Loan Amount | B11: Rs. 7,14,000
A12: Loan Purpose | B12: Vehicle/Equipment Purchase under Canara Vahan
A13: Tenor | B13: 7 Years (84 Months)
A14: Rate of Interest | B14: 9.50% p.a.
A15: Monthly EMI | B15: Rs. 12,844
A16: Total Amount Payable | B16: Rs. 10,78,896
A17: Total Interest Payable | B17: Rs. 3,64,896
A19: 3. FINANCIAL POSITION
A20: Financial Year | B20: FY 2025-26
A21: Gross Revenue (Estimate) | B21: Rs. 5,00,00,000 (To be updated with actual)
A22: EBITDA (Estimated) | B22: Rs. 1,50,00,000 (30% margin)
A23: Annual EMI Obligation | B23: Rs. 15,41,328 (12 x 12,844)
A24: DSCR | B24: ~2.75x (Healthy - Well above 1.50x minimum)
A26: 4. CREDIT STRENGTHS
A27: • Strong DSCR indicating comfortable debt service capacity
A28: • Canara Vahan scheme - Government-backed lending for transport sector
A29: • Reasonable ROI of 9.50% aligned with market rates
A30: • 12-13% annual growth assumption indicates positive business trajectory
A31: • Transport sector showing resilience in post-COVID economy
A33: 5. CREDIT CONCERNS & MITIGANTS
A34: Concern: Transport sector vulnerability to fuel price volatility & regulation changes
A35: → Mitigant: Adequate DSCR buffer to absorb cost fluctuations
A36: Concern: Vehicle collateral may depreciate rapidly
A37: → Mitigant: Monthly EMI collections provide regular cash flow monitoring
A38: Concern: Income verification from ITR documents (FY 2025-26 shows low tax)
... A54: APPROVED for loan amount of Rs. 7,14,000 under Canara Vahan scheme subject to: 1. Verification of financials from actual audited/ITR documents 2. Satisfactory collateral security (vehicle hypothecation) 3. Personal guarantee of proprietor 4. Comprehensive insurance coverage 5. Regular quarterly monitoring

Sheet Loan Summary
A1: CANARA BANK - CMA ANALYSIS
A2: CANARA VAHAN LOAN SCHEME
A4: LOAN DETAILS
A5: Borrower Name | B5: M/S. MALUSARE ENTERPRISES
A6: Proprietor | B6: MRS. SHILA KISHOR MALUSARE
A7: Business Type | B7: Transport/Vehicle (Canara Vahan)
A8: Loan Amount (Rs.) | B8: 714000
A9: Loan Tenure (Years) | B9: 7
A10: Rate of Interest (p.a.) | B10: 0.095
A11: Monthly Interest Rate | B11: =B8/12
A12: Total Number of Months | B12: 84
A14: MONTHLY EMI CALCULATION
A15: Monthly EMI (Rs.) | B15: 11669.603
A16: Total Amount to be Repaid | B16: =B12*B10
A17: Total Interest Payable | B17: =B13-B6
A19: KEY ASSUMPTIONS
A20: Average Annual Growth (Topline) | B20: 0.125
A21: Reference: FY 2025-26

Sheet Financials
A1: FINANCIAL ANALYSIS - HISTORICAL & PROJECTED
A2: Particulars | B2: FY 2023-24 | C2: FY 2024-25 | D2: FY 2025-26 | E2: FY 2026-27* | F2: FY 2027-28* | G2: FY 2028-29* | H2: FY 2029-30* | I2: FY 2030-31* | J2: FY 2031-32*
A3: OPERATING INCOME
A4: Gross Revenue (Rs. Lakh) | D4: 500 | E4: =D4*1.125 | F4: =E4*1.125 | G4: =F4*1.125 | H4: =G4*1.125 | I4: =H4*1.125
A5: Cost of Operations (% of Revenue) | B5: 0.7
A6: Cost of Operations (Rs. Lakh) | B6: =B4*$B$5 | C6: =C4*$B$5 | D6: =D4*$B$5 | E6: =E4*$B$5 | F6: =F4*$B$5 | G6: =G4*$B$5 | H6: =H4*$B$5 | I6: =I4*$B$5
A7: EBITDA (Rs. Lakh) | B7: =B4-B6 | C7: =C4-C6 | D7: =D4-D6 | E7: =E4-E6 | F7: =F4-F6 | G7: =G4-G6 | H7: =H4-H6 | I7: =I4-I6
A8: Depreciation (Rs. Lakh) | B8: 8 | C8: 8 | D8: 8 | E8: 8 | F8: 8 | G8: 8 | H8: 8 | I8: 8
A9: EBIT (Rs. Lakh) | B9: =B7-B8 | C9: =C7-C8 | D9: =D7-D8 | E9: =E7-E8 | F9: =F7-F8 | G9: =G7-G8 | H9: =H7-H8 | I9: =I7-I8
A10: Interest Expense - Term Loan (Rs. Lakh) | B10: 0 | C10: 0 | D10: 0 | E10: 0 | F10: 0 | G10: 0 | H10: 0 | I10: 0
A11: PBT (Rs. Lakh) | B11: =B9-B10 | C11: =C9-C10 | D11: =D9-D10 | E11: =E9-E10 | F11: =F9-F10 | G11: =G9-G10 | H11: =H9-H10 | I11: =I9-I10
A12: Tax @ 30% | B12: =MAX(0,B11)*0.30 | C12: =MAX(0,C11)*0.30 | D12: =MAX(0,D11)*0.30 | E12: =MAX(0,E11)*0.30 | F12: =MAX(0,F11)*0.30 | G12: =MAX(0,G11)*0.30 | H12: =MAX(0,H11)*0.30 | I12: =MAX(0,I11)*0.30
A13: PAT (Rs. Lakh) | B13: =B11-B12 | C13: =C11-C12 | D13: =D11-D12 | E13: =E11-E12 | F13: =F11-F12 | G13: =G11-G12 | H13: =H11-H12 | I13: =I11-I12

Sheet Debt Service
A1: LOAN AMORTIZATION SCHEDULE
A3: Year | B3: Opening Balance (Rs.) | C3: Annual EMI (Rs.) | D3: Principal Portion (Rs.) | E3: Interest Portion (Rs.) | F3: Closing Balance (Rs.) | G3: Cumulative Principal Paid | H3: Principal % of EMI | I3: Interest % of EMI
A4: Year 1 | B4: 714000 | C4: 140035.24 | D4: =C4-E4 | E4: =B4*0.095 | F4: =B4-D4 | G4: =D4 | H4: =D4/C4 | I4: =E4/C4
A5: Year 2 | B5: =F4 | C5: 140035.24 | D5: =C5-E5 | E5: =B5*0.095 | F5: =B5-D5 | G5: =G4+D5 | H5: =D5/C5 | I5: =E5/C5
A6: Year 3 | B6: =F5 | C6: 140035.24 | D6: =C6-E6 | E6: =B6*0.095 | F6: =B6-D6 | G6: =G5+D6 | H6: =D6/C6 | I6: =E6/C6
A7: Year 4 | B7: =F6 | C7: 140035.24 | D7: =C7-E7 | E7: =B7*0.095 | F7: =B7-D7 | G7: =G6+D7 | H7: =D7/C7 | I7: =E7/C7
A8: Year 5 | B8: =F7 | C8: 140035.24 | D8: =C8-E8 | E8: =B8*0.095 | F8: =B8-D8 | G8: =G7+D8 | H8: =D8/C8 | I8: =E8/C8
A9: Year 6 | B9: =F8 | C9: 140035.24 | D9: =C9-E9 | E9: =B9*0.095 | F9: =B9-D9 | G9: =G8+D9 | H9: =D9/C9 | I9: =E9/C9
A10: Year 7 | B10: =F9 | C10: 140035.24 | D10: =C10-E10 | E10: =B10*0.095 | F10: =B10-D10 | G10: =G9+D10 | H10: =D10/C10 | I10: =E10/C10
A13: TOTAL REPAYMENT | C13: =SUM(C5:C12)
A14: TOTAL INTEREST PAID | E14: =SUM(E5:E12)

Sheet Ratios & Covenants
A1: FINANCIAL RATIOS & DEBT COVENANTS ANALYSIS
A3: KEY PROFITABILITY RATIOS
A4: Ratio | B4: FY 2025-26 | C4: Industry Benchmark
A5: Gross Profit Margin (%) | B5: =((D3-D5)/D3)*100 | C5: 18-22%
A6: EBITDA Margin (%) | B6: =(D6/D3)*100 | C6: 18-25%
A7: Net Profit Margin (%) | B7: =(D11/D3)*100 | C7: 8-12%
A9: DEBT SERVICE RATIOS
A10: Ratio | B10: FY 2025-26 | C10: Acceptable
A11: Debt Service Coverage Ratio (DSCR) | B11: =(D6)/(12*12.84) | C11: > 1.50x
A12: Interest Coverage Ratio | B12: =(D6)/(D9) | C12: > 2.50x
A13: Loan to Value Ratio | B13: =7.14/(D3/100) | C13: < 50%
A15: REPAYMENT CAPACITY ANALYSIS
A16: Annual EMI | B16: =12*12.84
A17: Annual EBITDA (Lakh) | B17: =D6
A18: Available for Debt Service (Lakh) | B18: =(D6-D10)/100
A19: Debt Service Capacity | B19: =(D6*100)/(12*12.84) | C19: Adequate if > 1.50x

Sheet Cash Flow
A1: CASH FLOW PROJECTION (7 YEARS)
A3: Particulars | B3: FY 2026-27 | C3: FY 2027-28 | D3: FY 2028-29 | E3: FY 2029-30 | F3: FY 2030-31 | G3: FY 2031-32 | H3: Terminal
A4: Operating Cash Flow (EBITDA) | B4: =Financials!E6 | C4: =Financials!F6 | D4: =Financials!G6 | E4: =Financials!H6 | F4: =Financials!I6 | G4: =Financials!J6 | H4: =Financials!K6
A5: Less: Interest Expense | B5: ='Debt Service'!F7 | C5: ='Debt Service'!G8 | D5: ='Debt Service'!H9 | E5: ='Debt Service'!I10 | F5: ='Debt Service'!J11 | G5: ='Debt Service'!K12 | H5: ='Debt Service'!L13
A6: Less: Taxes | B6: =Financials!E10 | C6: =Financials!F10 | D6: =Financials!G10 | E6: =Financials!H10 | F6: =Financials!I10 | G6: =Financials!J10 | H6: =Financials!K10
A7: Free Cash Flow Available | B7: =B4-B5-B6 | C7: =C4-C5-C6 | D7: =D4-D5-D6 | E7: =E4-E5-E6 | F7: =F4-F5-F6 | G7: =G4-G5-G6 | H7: =H4-H5-H6
A8: Less: Principal Repayment | B8: ='Debt Service'!D7 | C8: ='Debt Service'!E8 | D8: ='Debt Service'!F9 | E8: ='Debt Service'!G10 | F8: ='Debt Service'!H11 | G8: ='Debt Service'!I12 | H8: ='Debt Service'!J13
A9: Residual Cash Flow | B9: =B7-B8 | C9: =C7-C8 | D9: =D7-D8 | E9: =E7-E8 | F9: =F7-F8 | G9: =G7-G8 | H9: =H7-H8
